{
  "title": "Conclusion",
  "outline": [],
  "memory_optimization": {
    "enabled": true,
    "streaming_used": false,
    "memory_usage": {
      "rss_mb": 827.9765625,
      "vms_mb": 1550.76953125,
      "percent": 3.4795475908513516
    },
    "cache_stats": {
      "total_items": 0,
      "total_size_mb": 0.0,
      "max_size_mb": 500.0,
      "utilization": 0.0
    }
  },
  "source_pdf": "The Ultimate PDF Sharing Checklist.pdf",
  "generated_by": "Round1A_OptimizedEngine",
  "generation_time": "2025-07-27T19:23:00.024190",
  "processing_time_seconds": 0.76
}